Metadata-Version: 1.2
Name: my-settings
Version: 0.1.1
Summary: Convenient and simple settings for any project
Home-page: https://github.com/GregEremeev/my_settings
Author: Greg Eremeev
Author-email: gregory.eremeev@gmail.com
License: MIT
Platform: any
Classifier: Development Status :: 3 - Alpha
Classifier: Intended Audience :: Developers
Classifier: License :: OSI Approved :: MIT License
Classifier: Programming Language :: Python :: 3.3
Classifier: Programming Language :: Python :: 3.4
Classifier: Programming Language :: Python :: 3.5
Classifier: Programming Language :: Python :: 3.6
Requires-Python: >=3.3
